matematik/__init__.py
matematik/arithmetic/__init__.py
matematik/arithmetic/add.py
matematik/arithmetic/decimals.py
matematik/arithmetic/divide.py
matematik/arithmetic/fractions.py
matematik/arithmetic/multiply.py
matematik/arithmetic/negative_nums.py
matematik/arithmetic/subtract.py
matematik/formula/__init__.py
matematik/formula/algebra1.py
matematik/formula/algebra2.py
matematik/formula/arithmetic.py
matematik/formula/calculus.py
matematik/formula/geometry.py
matematik/formula/precalculus.py
matematik/formula/trigonometry.py
tests/__init__.py
tests/formula/__init__.py
tests/formula/test_algebra1.py
tests/formula/test_algebra2.py
tests/formula/test_arithmetic.py
tests/formula/test_geometry.py
matematik-1.2.1.dist-info/LICENSE
matematik-1.2.1.dist-info/METADATA
matematik-1.2.1.dist-info/WHEEL
matematik-1.2.1.dist-info/top_level.txt
matematik-1.2.1.dist-info/RECORD
