Metadata-Version: 2.1
Name: matematik
Version: 1.2.1
Summary: An package for solving math equations
Home-page: https://github.com/demirantay/matematik
Author: Demir Antay
Author-email: demir99antay@gmail.com
License: UNKNOWN
Platform: UNKNOWN
